tradfricoap/__init__.py
tradfricoap/cli.py
tradfricoap/coapcmd_api.py
tradfricoap/colors.py
tradfricoap/config.py
tradfricoap/constants.py
tradfricoap/device.py
tradfricoap/device_info.py
tradfricoap/errors.py
tradfricoap/gateway.py
tradfricoap/pycoap_api.py
tradfricoap/request.py
tradfricoap-0.0.4.data/scripts/tradfri
tradfricoap-0.0.4.dist-info/LICENSE
tradfricoap-0.0.4.dist-info/METADATA
tradfricoap-0.0.4.dist-info/WHEEL
tradfricoap-0.0.4.dist-info/top_level.txt
tradfricoap-0.0.4.dist-info/RECORD
